foxglove_data_platform/__init__.py
foxglove_data_platform/client.py
foxglove_data_platform/py.typed
tests/__init__.py
tests/api_url.py
tests/generate.py
tests/string_message_pb2.py
tests/test_attachments.py
tests/test_client.py
tests/test_coverage.py
tests/test_data.py
tests/test_devices.py
tests/test_events.py
tests/test_imports.py
tests/test_json_messages.py
tests/test_protobuf_messages.py
tests/test_recordings.py
tests/test_ros1_messages.py
tests/test_ros2_messages.py
tests/test_stream_messages.py
foxglove_data_platform-0.14.2.dist-info/LICENSE
foxglove_data_platform-0.14.2.dist-info/METADATA
foxglove_data_platform-0.14.2.dist-info/WHEEL
foxglove_data_platform-0.14.2.dist-info/top_level.txt
foxglove_data_platform-0.14.2.dist-info/RECORD
