Metadata-Version: 2.1
Name: foxglove-data-platform
Version: 0.14.2
Summary: Client library for Foxglove Data Platform.
Home-page: https://github.com/foxglove/py-data-platform
Classifier: Programming Language :: Python :: 3
Classifier: License :: OSI Approved :: MIT License
Classifier: Operating System :: OS Independent
Requires-Python: >=3.7
License-File: LICENSE
Requires-Dist: arrow
Requires-Dist: requests
Requires-Dist: typing-extensions
Requires-Dist: mcap >=1.1.0
